{"items": [{"loc_details": [], "byte_offset": 2, "uri": "", "pos": "vn", "ne": "", "item": "比赛", "basic_words": ["比赛"], "byte_length": 4, "formal": ""}, {"loc_details": [], "byte_offset": 6, "uri": "", "pos": "f", "ne": "", "item": "中", "basic_words": ["中"], "byte_length": 2, "formal": ""}, {"loc_details": [], "byte_offset": 8, "uri": "", "pos": "v", "ne": "", "item": "寻找", "basic_words": ["寻找"], "byte_length": 4, "formal": ""}, {"loc_details": [], "byte_offset": 12, "uri": "", "pos": "vn", "ne": "", "item": "运动", "basic_words": ["运动"], "byte_length": 4, "formal": ""}, {"loc_details": [], "byte_offset": 18, "uri": "", "pos": "n", "ne": "", "item": "真谛", "basic_words": ["真谛"], "byte_length": 4, "formal": ""}, {"loc_details": [], "byte_offset": 24, "uri": "", "pos": "", "ne": "ORG", "item": "西南交通大学", "basic_words": ["西南", "交通", "大学"], "byte_length": 12, "formal": ""}, {"loc_details": [], "byte_offset": 36, "uri": "", "pos": "", "ne": "LOC", "item": "新闻", "basic_words": ["新闻"], "byte_length": 4, "formal": ""}, {"loc_details": [], "byte_offset": 40, "uri": "", "pos": "n", "ne": "", "item": "网", "basic_words": ["网"], "byte_length": 2, "formal": ""}, {"loc_details": [], "byte_offset": 42, "uri": "", "pos": "", "ne": "ORG", "item": "西南交通大学新闻中心", "basic_words": ["西南", "交通", "大学", "新闻", "中心"], "byte_length": 20, "formal": ""}, {"loc_details": [], "byte_offset": 62, "uri": "", "pos": "v", "ne": "", "item": "主办", "basic_words": ["主办"], "byte_length": 4, "formal": ""}, {"loc_details": [], "byte_offset": 66, "uri": "", "pos": "nz", "ne": "", "item": "  \n\n\t\n\n\t", "basic_words": ["  ", "\n\n\t", "\n\n\t"], "byte_length": 8, "formal": ""}, {"loc_details": [], "byte_offset": 74, "uri": "", "pos": "", "ne": "TIME", "item": "4月15日下午", "basic_words": ["4", "月", "15", "日", "下午"], "byte_length": 11, "formal": ""}, {"loc_details": [], "byte_offset": 87, "uri": "", "pos": "p", "ne": "", "item": "对着", "basic_words": ["对着"], "byte_length": 4, "formal": ""}, {"loc_details": [], "byte_offset": 91, "uri": "", "pos": "a", "ne": "", "item": "如火", "basic_words": ["如", "火"], "byte_length": 4, "formal": ""}, {"loc_details": [], "byte_offset": 97, "uri": "", "pos": "n", "ne": "", "item": "骄阳", "basic_words": ["骄阳"], "byte_length": 4, "formal": ""}, {"loc_details": [], "byte_offset": 103, "uri": "", "pos": "v", "ne": "", "item": "迎", "basic_words": ["迎"], "byte_length": 2, "formal": ""}, {"loc_details": [], "byte_offset": 107, "uri": "", "pos": "", "ne": "TIME", "item": "四月", "basic_words": ["四月"], "byte_length": 4, "formal": ""}, {"loc_details": [], "byte_offset": 113, "uri": "", "pos": "n", "ne": "", "item": "花香", "basic_words": ["花香"], "byte_length": 4, "formal": ""}, {"loc_details": [], "byte_offset": 119, "uri": "", "pos": "", "ne": "ORG", "item": "交大", "basic_words": ["交大"], "byte_length": 4, "formal": ""}, {"loc_details": [], "byte_offset": 123, "uri": "", "pos": "n", "ne": "", "item": "学子", "basic_words": ["学子"], "byte_length": 4, "formal": ""}, {"loc_details": [], "byte_offset": 131, "uri": "", "pos": "v", "ne": "", "item": "齐聚", "basic_words": ["齐聚"], "byte_length": 4, "formal": ""}, {"loc_details": [], "byte_offset": 135, "uri": "", "pos": "", "ne": "LOC", "item": "北区", "basic_words": ["北", "区"], "byte_length": 4, "formal": ""}, {"loc_details": [], "byte_offset": 139, "uri": "", "pos": "n", "ne": "", "item": "体育场", "basic_words": ["体育", "场"], "byte_length": 6, "formal": ""}, {"loc_details": [], "byte_offset": 147, "uri": "", "pos": "v", "ne": "", "item": "展开", "basic_words": ["展开"], "byte_length": 4, "formal": ""}, {"loc_details": [], "byte_offset": 151, "uri": "", "pos": "r", "ne": "", "item": "本届", "basic_words": ["本", "届"], "byte_length": 4, "formal": ""}, {"loc_details": [], "byte_offset": 155, "uri": "", "pos": "n", "ne": "", "item": "运动会", "basic_words": ["运动", "会"], "byte_length": 6, "formal": ""}, {"loc_details": [], "byte_offset": 161, "uri": "", "pos": "n", "ne": "", "item": "最后的较量", "basic_words": ["最后", "的", "较量"], "byte_length": 10, "formal": ""}, {"loc_details": [], "byte_offset": 173, "uri": "", "pos": "nr", "ne": "", "item": "\n\n\n\n\t", "basic_words": ["\n\n\n", "\n\t"], "byte_length": 5, "formal": ""}, {"loc_details": [], "byte_offset": 178, "uri": "", "pos": "m", "ne": "", "item": "两点", "basic_words": ["两点"], "byte_length": 4, "formal": ""}, {"loc_details": [], "byte_offset": 188, "uri": "", "pos": "n", "ne": "", "item": "看台", "basic_words": ["看", "台"], "byte_length": 4, "formal": ""}, {"loc_details": [], "byte_offset": 196, "uri": "", "pos": "v", "ne": "", "item": "备", "basic_words": ["备"], "byte_length": 2, "formal": ""}, {"loc_details": [], "byte_offset": 200, "uri": "", "pos": "vn", "ne": "", "item": "遮阳", "basic_words": ["遮阳"], "byte_length": 4, "formal": ""}, {"loc_details": [], "byte_offset": 204, "uri": "", "pos": "n", "ne": "", "item": "工具", "basic_words": ["工具"], "byte_length": 4, "formal": ""}, {"loc_details": [], "byte_offset": 210, "uri": "", "pos": "n", "ne": "", "item": "观众", "basic_words": ["观众"], "byte_length": 4, "formal": ""}, {"loc_details": [], "byte_offset": 216, "uri": "", "pos": "n", "ne": "", "item": "裁判席", "basic_words": ["裁判", "席"], "byte_length": 6, "formal": ""}, {"loc_details": [], "byte_offset": 226, "uri": "", "pos": "v", "ne": "", "item": "核对", "basic_words": ["核对"], "byte_length": 4, "formal": ""}, {"loc_details": [], "byte_offset": 230, "uri": "", "pos": "n", "ne": "", "item": "名单", "basic_words": ["名单"], "byte_length": 4, "formal": ""}, {"loc_details": [], "byte_offset": 236, "uri": "", "pos": "n", "ne": "", "item": "裁判", "basic_words": ["裁判"], "byte_length": 4, "formal": ""}, {"loc_details": [], "byte_offset": 242, "uri": "", "pos": "v", "ne": "", "item": "奔走", "basic_words": ["奔走"], "byte_length": 4, "formal": ""}, {"loc_details": [], "byte_offset": 248, "uri": "", "pos": "v", "ne": "", "item": "汗流浃背", "basic_words": ["汗流浃背"], "byte_length": 8, "formal": ""}, {"loc_details": [], "byte_offset": 258, "uri": "", "pos": "vn", "ne": "", "item": "工作", "basic_words": ["工作"], "byte_length": 4, "formal": ""}, {"loc_details": [], "byte_offset": 262, "uri": "", "pos": "n", "ne": "", "item": "人员", "basic_words": ["人员"], "byte_length": 4, "formal": ""}, {"loc_details": [], "byte_offset": 270, "uri": "", "pos": "n", "ne": "", "item": "衣着", "basic_words": ["衣着"], "byte_length": 4, "formal": ""}, {"loc_details": [], "byte_offset": 274, "uri": "", "pos": "a", "ne": "", "item": "干练", "basic_words": ["干练"], "byte_length": 4, "formal": ""}, {"loc_details": [], "byte_offset": 278, "uri": "", "pos": "v", "ne": "", "item": "跃跃欲试", "basic_words": ["跃跃欲试"], "byte_length": 8, "formal": ""}, {"loc_details": [], "byte_offset": 288, "uri": "", "pos": "n", "ne": "", "item": "参赛选手们", "basic_words": ["参赛", "选手", "们"], "byte_length": 10, "formal": ""}, {"loc_details": [], "byte_offset": 310, "uri": "", "pos": "n", "ne": "", "item": "位置", "basic_words": ["位置"], "byte_length": 4, "formal": ""}, {"loc_details": [], "byte_offset": 316, "uri": "", "pos": "v", "ne": "", "item": "做好准备", "basic_words": ["做", "好", "准备"], "byte_length": 8, "formal": ""}, {"loc_details": [], "byte_offset": 326, "uri": "", "pos": "v", "ne": "", "item": "等待", "basic_words": ["等待"], "byte_length": 4, "formal": ""}, {"loc_details": [], "byte_offset": 330, "uri": "", "pos": "vn", "ne": "", "item": "比赛", "basic_words": ["比赛"], "byte_length": 4, "formal": ""}, {"loc_details": [], "byte_offset": 342, "uri": "", "pos": "", "ne": "TIME", "item": "下午两点半", "basic_words": ["下午", "两点", "半"], "byte_length": 10, "formal": ""}, {"loc_details": [], "byte_offset": 354, "uri": "", "pos": "vn", "ne": "", "item": "比赛", "basic_words": ["比赛"], "byte_length": 4, "formal": ""}, {"loc_details": [], "byte_offset": 358, "uri": "", "pos": "ad", "ne": "", "item": "正式", "basic_words": ["正式"], "byte_length": 4, "formal": ""}, {"loc_details": [], "byte_offset": 368, "uri": "", "pos": "n", "ne": "", "item": "体育场", "basic_words": ["体育", "场"], "byte_length": 6, "formal": ""}, {"loc_details": [], "byte_offset": 376, "uri": "", "pos": "vn", "ne": "", "item": "擂鼓", "basic_words": ["擂鼓"], "byte_length": 4, "formal": ""}, {"loc_details": [], "byte_offset": 380, "uri": "", "pos": "n", "ne": "", "item": "声", "basic_words": ["声"], "byte_length": 2, "formal": ""}, {"loc_details": [], "byte_offset": 384, "uri": "", "pos": "vn", "ne": "", "item": "欢呼", "basic_words": ["欢呼"], "byte_length": 4, "formal": ""}, {"loc_details": [], "byte_offset": 388, "uri": "", "pos": "n", "ne": "", "item": "声响", "basic_words": ["声", "响"], "byte_length": 4, "formal": ""}, {"loc_details": [], "byte_offset": 392, "uri": "", "pos": "m", "ne": "", "item": "成一片", "basic_words": ["成", "一", "片"], "byte_length": 6, "formal": ""}, {"loc_details": [], "byte_offset": 400, "uri": "", "pos": "n", "ne": "", "item": "赛场", "basic_words": ["赛", "场"], "byte_length": 4, "formal": ""}, {"loc_details": [], "byte_offset": 406, "uri": "", "pos": "v", "ne": "", "item": "飞梭", "basic_words": ["飞梭"], "byte_length": 4, "formal": ""}, {"loc_details": [], "byte_offset": 412, "uri": "", "pos": "n", "ne": "", "item": "身影", "basic_words": ["身影"], "byte_length": 4, "formal": ""}, {"loc_details": [], "byte_offset": 418, "uri": "", "pos": "v", "ne": "", "item": "专注", "basic_words": ["专注"], "byte_length": 4, "formal": ""}, {"loc_details": [], "byte_offset": 424, "uri": "", "pos": "n", "ne": "", "item": "神情", "basic_words": ["神", "情"], "byte_length": 4, "formal": ""}, {"loc_details": [], "byte_offset": 428, "uri": "", "pos": "v", "ne": "", "item": "交", "basic_words": ["交"], "byte_length": 2, "formal": ""}, {"loc_details": [], "byte_offset": 430, "uri": "", "pos": "v", "ne": "", "item": "相呼应", "basic_words": ["相", "呼应"], "byte_length": 6, "formal": ""}, {"loc_details": [], "byte_offset": 438, "uri": "", "pos": "nt", "ne": "", "item": "\n\n\n\n\t4X", "basic_words": ["\n\n\n", "\n\t", "4X"], "byte_length": 7, "formal": ""}, {"loc_details": [], "byte_offset": 445, "uri": "", "pos": "m", "ne": "", "item": "400", "basic_words": ["400"], "byte_length": 3, "formal": ""}, {"loc_details": [], "byte_offset": 448, "uri": "", "pos": "n", "ne": "", "item": "接力赛", "basic_words": ["接力", "赛"], "byte_length": 6, "formal": ""}, {"loc_details": [], "byte_offset": 458, "uri": "", "pos": "n", "ne": "", "item": "两手", "basic_words": ["两手"], "byte_length": 4, "formal": ""}, {"loc_details": [], "byte_offset": 464, "uri": "", "pos": "vn", "ne": "", "item": "交", "basic_words": ["交"], "byte_length": 2, "formal": ""}, {"loc_details": [], "byte_offset": 468, "uri": "", "pos": "v", "ne": "", "item": "信任", "basic_words": ["信任"], "byte_length": 4, "formal": ""}, {"loc_details": [], "byte_offset": 472, "uri": "", "pos": "nz", "ne": "", "item": "\n\n\n\n\t ", "basic_words": ["\n\n\n", "\n\t "], "byte_length": 6, "formal": ""}, {"loc_details": [], "byte_offset": 478, "uri": "", "pos": "v", "ne": "", "item": "检录", "basic_words": ["检", "录"], "byte_length": 4, "formal": ""}, {"loc_details": [], "byte_offset": 482, "uri": "", "pos": "v", "ne": "", "item": "完毕", "basic_words": ["完毕"], "byte_length": 4, "formal": ""}, {"loc_details": [], "byte_offset": 490, "uri": "", "pos": "v", "ne": "", "item": "穿", "basic_words": ["穿"], "byte_length": 2, "formal": ""}, {"loc_details": [], "byte_offset": 494, "uri": "", "pos": "n", "ne": "", "item": "号码", "basic_words": ["号码"], "byte_length": 4, "formal": ""}, {"loc_details": [], "byte_offset": 498, "uri": "", "pos": "v", "ne": "", "item": "簿", "basic_words": ["簿"], "byte_length": 2, "formal": ""}, {"loc_details": [], "byte_offset": 502, "uri": "", "pos": "n", "ne": "", "item": "运动员们", "basic_words": ["运动", "员", "们"], "byte_length": 8, "formal": ""}, {"loc_details": [], "byte_offset": 512, "uri": "", "pos": "vn", "ne": "", "item": "工作", "basic_words": ["工作"], "byte_length": 4, "formal": ""}, {"loc_details": [], "byte_offset": 516, "uri": "", "pos": "n", "ne": "", "item": "人员", "basic_words": ["人员"], "byte_length": 4, "formal": ""}, {"loc_details": [], "byte_offset": 522, "uri": "", "pos": "vn", "ne": "", "item": "带领", "basic_words": ["带领"], "byte_length": 4, "formal": ""}, {"loc_details": [], "byte_offset": 528, "uri": "", "pos": "v", "ne": "", "item": "来到", "basic_words": ["来到"], "byte_length": 4, "formal": ""}, {"loc_details": [], "byte_offset": 534, "uri": "", "pos": "n", "ne": "", "item": "赛道", "basic_words": ["赛道"], "byte_length": 4, "formal": ""}, {"loc_details": [], "byte_offset": 540, "uri": "", "pos": "n", "ne": "", "item": "起点", "basic_words": ["起点"], "byte_length": 4, "formal": ""}, {"loc_details": [], "byte_offset": 548, "uri": "", "pos": "n", "ne": "", "item": "起点处", "basic_words": ["起点", "处"], "byte_length": 6, "formal": ""}, {"loc_details": [], "byte_offset": 556, "uri": "", "pos": "m", "ne": "", "item": "第一棒", "basic_words": ["第", "一", "棒"], "byte_length": 6, "formal": ""}, {"loc_details": [], "byte_offset": 562, "uri": "", "pos": "n", "ne": "", "item": "选手", "basic_words": ["选手"], "byte_length": 4, "formal": ""}, {"loc_details": [], "byte_offset": 566, "uri": "", "pos": "v", "ne": "", "item": "做", "basic_words": ["做"], "byte_length": 2, "formal": ""}, {"loc_details": [], "byte_offset": 576, "uri": "", "pos": "vn", "ne": "", "item": "调整", "basic_words": ["调整"], "byte_length": 4, "formal": ""}, {"loc_details": [], "byte_offset": 580, "uri": "", "pos": "n", "ne": "", "item": "工作", "basic_words": ["工作"], "byte_length": 4, "formal": ""}, {"loc_details": [], "byte_offset": 594, "uri": "", "pos": "v", "ne": "", "item": "弯腰", "basic_words": ["弯腰"], "byte_length": 4, "formal": ""}, {"loc_details": [], "byte_offset": 598, "uri": "", "pos": "a", "ne": "", "item": "紧", "basic_words": ["紧"], "byte_length": 2, "formal": ""}, {"loc_details": [], "byte_offset": 600, "uri": "", "pos": "n", "ne": "", "item": "鞋带", "basic_words": ["鞋带"], "byte_length": 4, "formal": ""}, {"loc_details": [], "byte_offset": 612, "uri": "", "pos": "n", "ne": "", "item": "原地", "basic_words": ["原地"], "byte_length": 4, "formal": ""}, {"loc_details": [], "byte_offset": 616, "uri": "", "pos": "v", "ne": "", "item": "做", "basic_words": ["做"], "byte_length": 2, "formal": ""}, {"loc_details": [], "byte_offset": 618, "uri": "", "pos": "n", "ne": "", "item": "收腹", "basic_words": ["收腹"], "byte_length": 4, "formal": ""}, {"loc_details": [], "byte_offset": 622, "uri": "", "pos": "vn", "ne": "", "item": "起跳", "basic_words": ["起跳"], "byte_length": 4, "formal": ""}, {"loc_details": [], "byte_offset": 638, "uri": "", "pos": "d", "ne": "", "item": "往前", "basic_words": ["往前"], "byte_length": 4, "formal": ""}, {"loc_details": [], "byte_offset": 642, "uri": "", "pos": "v", "ne": "", "item": "试", "basic_words": ["试"], "byte_length": 2, "formal": ""}, {"loc_details": [], "byte_offset": 644, "uri": "", "pos": "v", "ne": "", "item": "跑", "basic_words": ["跑"], "byte_length": 2, "formal": ""}, {"loc_details": [], "byte_offset": 646, "uri": "", "pos": "", "ne": "PER", "item": "几米", "basic_words": ["几米"], "byte_length": 4, "formal": ""}, {"loc_details": [], "byte_offset": 656, "uri": "", "pos": "n", "ne": "", "item": "赛道", "basic_words": ["赛道"], "byte_length": 4, "formal": ""}, {"loc_details": [], "byte_offset": 664, "uri": "", "pos": "n", "ne": "", "item": "裁判", "basic_words": ["裁判"], "byte_length": 4, "formal": ""}, {"loc_details": [], "byte_offset": 668, "uri": "", "pos": "v", "ne": "", "item": "举起", "basic_words": ["举起"], "byte_length": 4, "formal": ""}, {"loc_details": [], "byte_offset": 672, "uri": "", "pos": "n", "ne": "", "item": "发令", "basic_words": ["发令"], "byte_length": 4, "formal": ""}, {"loc_details": [], "byte_offset": 676, "uri": "", "pos": "n", "ne": "", "item": "枪", "basic_words": ["枪"], "byte_length": 2, "formal": ""}, {"loc_details": [], "byte_offset": 678, "uri": "", "pos": "v", "ne": "", "item": "高喊", "basic_words": ["高喊"], "byte_length": 4, "formal": ""}, {"loc_details": [], "byte_offset": 686, "uri": "", "pos": "v", "ne": "", "item": "就位", "basic_words": ["就位"], "byte_length": 4, "formal": ""}, {"loc_details": [], "byte_offset": 692, "uri": "", "pos": "n", "ne": "", "item": "时", "basic_words": ["时"], "byte_length": 2, "formal": ""}, {"loc_details": [], "byte_offset": 706, "uri": "", "pos": "n", "ne": "", "item": "双手", "basic_words": ["双手"], "byte_length": 4, "formal": ""}, {"loc_details": [], "byte_offset": 710, "uri": "", "pos": "v", "ne": "", "item": "俯", "basic_words": ["俯"], "byte_length": 2, "formal": ""}, {"loc_details": [], "byte_offset": 716, "uri": "", "pos": "n", "ne": "", "item": "两眼", "basic_words": ["两眼"], "byte_length": 4, "formal": ""}, {"loc_details": [], "byte_offset": 720, "uri": "", "pos": "v", "ne": "", "item": "目视", "basic_words": ["目", "视"], "byte_length": 4, "formal": ""}, {"loc_details": [], "byte_offset": 724, "uri": "", "pos": "f", "ne": "", "item": "前方", "basic_words": ["前方"], "byte_length": 4, "formal": ""}, {"loc_details": [], "byte_offset": 730, "uri": "", "pos": "m", "ne": "", "item": "两耳", "basic_words": ["两", "耳"], "byte_length": 4, "formal": ""}, {"loc_details": [], "byte_offset": 734, "uri": "", "pos": "v", "ne": "", "item": "聚精会神", "basic_words": ["聚精会神"], "byte_length": 8, "formal": ""}, {"loc_details": [], "byte_offset": 744, "uri": "", "pos": "v", "ne": "", "item": "听", "basic_words": ["听"], "byte_length": 2, "formal": ""}, {"loc_details": [], "byte_offset": 748, "uri": "", "pos": "r", "ne": "", "item": "下一步", "basic_words": ["下", "一", "步"], "byte_length": 6, "formal": ""}, {"loc_details": [], "byte_offset": 754, "uri": "", "pos": "n", "ne": "", "item": "命令", "basic_words": ["命令"], "byte_length": 4, "formal": ""}, {"loc_details": [], "byte_offset": 760, "uri": "", "pos": "nr", "ne": "", "item": "\n\n\n\n\t", "basic_words": ["\n\n\n", "\n\t"], "byte_length": 5, "formal": ""}, {"loc_details": [], "byte_offset": 765, "uri": "", "pos": "m", "ne": "", "item": "第一棒", "basic_words": ["第", "一", "棒"], "byte_length": 6, "formal": ""}, {"loc_details": [], "byte_offset": 771, "uri": "", "pos": "n", "ne": "", "item": "选手", "basic_words": ["选手"], "byte_length": 4, "formal": ""}, {"loc_details": [], "byte_offset": 777, "uri": "", "pos": "m", "ne": "", "item": "一声", "basic_words": ["一声"], "byte_length": 4, "formal": ""}, {"loc_details": [], "byte_offset": 781, "uri": "", "pos": "v", "ne": "", "item": "枪响", "basic_words": ["枪响"], "byte_length": 4, "formal": ""}, {"loc_details": [], "byte_offset": 789, "uri": "", "pos": "v", "ne": "", "item": "争先恐后", "basic_words": ["争先恐后"], "byte_length": 8, "formal": ""}, {"loc_details": [], "byte_offset": 799, "uri": "", "pos": "v", "ne": "", "item": "绕", "basic_words": ["绕"], "byte_length": 2, "formal": ""}, {"loc_details": [], "byte_offset": 801, "uri": "", "pos": "n", "ne": "", "item": "赛道", "basic_words": ["赛道"], "byte_length": 4, "formal": ""}, {"loc_details": [], "byte_offset": 805, "uri": "", "pos": "", "ne": "TIME", "item": "一周", "basic_words": ["一", "周"], "byte_length": 4, "formal": ""}, {"loc_details": [], "byte_offset": 813, "uri": "", "pos": "v", "ne": "", "item": "回到起点", "basic_words": ["回到", "起点"], "byte_length": 8, "formal": ""}, {"loc_details": [], "byte_offset": 821, "uri": "", "pos": "n", "ne": "", "item": "时", "basic_words": ["时"], "byte_length": 2, "formal": ""}, {"loc_details": [], "byte_offset": 827, "uri": "", "pos": "n", "ne": "", "item": "接力棒", "basic_words": ["接力", "棒"], "byte_length": 6, "formal": ""}, {"loc_details": [], "byte_offset": 833, "uri": "", "pos": "v", "ne": "", "item": "交给", "basic_words": ["交给"], "byte_length": 4, "formal": ""}, {"loc_details": [], "byte_offset": 837, "uri": "", "pos": "m", "ne": "", "item": "第二棒", "basic_words": ["第", "二", "棒"], "byte_length": 6, "formal": ""}, {"loc_details": [], "byte_offset": 843, "uri": "", "pos": "n", "ne": "", "item": "选手", "basic_words": ["选手"], "byte_length": 4, "formal": ""}, {"loc_details": [], "byte_offset": 851, "uri": "", "pos": "v", "ne": "", "item": "跑", "basic_words": ["跑"], "byte_length": 2, "formal": ""}, {"loc_details": [], "byte_offset": 855, "uri": "", "pos": "n", "ne": "", "item": "速度", "basic_words": ["速度"], "byte_length": 4, "formal": ""}, {"loc_details": [], "byte_offset": 877, "uri": "", "pos": "n", "ne": "", "item": "接力棒", "basic_words": ["接力", "棒"], "byte_length": 6, "formal": ""}, {"loc_details": [], "byte_offset": 885, "uri": "", "pos": "vn", "ne": "", "item": "交接", "basic_words": ["交接"], "byte_length": 4, "formal": ""}, {"loc_details": [], "byte_offset": 889, "uri": "", "pos": "a", "ne": "", "item": "更重要", "basic_words": ["更", "重要"], "byte_length": 6, "formal": ""}, {"loc_details": [], "byte_offset": 903, "uri": "", "pos": "", "ne": "LOC", "item": "峨眉校区", "basic_words": ["峨眉", "校区"], "byte_length": 8, "formal": ""}, {"loc_details": [], "byte_offset": 913, "uri": "", "pos": "n", "ne": "", "item": "女子", "basic_words": ["女子"], "byte_length": 4, "formal": ""}, {"loc_details": [], "byte_offset": 917, "uri": "", "pos": "n", "ne": "", "item": "甲组", "basic_words": ["甲组"], "byte_length": 4, "formal": ""}, {"loc_details": [], "byte_offset": 921, "uri": "", "pos": "n", "ne": "", "item": "冠军", "basic_words": ["冠军"], "byte_length": 4, "formal": ""}, {"loc_details": [], "byte_offset": 925, "uri": "", "pos": "n", "ne": "", "item": "队伍", "basic_words": ["队伍"], "byte_length": 4, "formal": ""}, {"loc_details": [], "byte_offset": 931, "uri": "", "pos": "", "ne": "PER", "item": "张文莉", "basic_words": ["张", "文莉"], "byte_length": 6, "formal": ""}, {"loc_details": [], "byte_offset": 937, "uri": "", "pos": "v", "ne": "", "item": "如是说", "basic_words": ["如", "是", "说"], "byte_length": 6, "formal": ""}, {"loc_details": [], "byte_offset": 951, "uri": "", "pos": "vn", "ne": "", "item": "比赛", "basic_words": ["比赛"], "byte_length": 4, "formal": ""}, {"loc_details": [], "byte_offset": 955, "uri": "", "pos": "f", "ne": "", "item": "中", "basic_words": ["中"], "byte_length": 2, "formal": ""}, {"loc_details": [], "byte_offset": 959, "uri": "", "pos": "", "ne": "PER", "item": "张文莉", "basic_words": ["张文莉"], "byte_length": 6, "formal": ""}, {"loc_details": [], "byte_offset": 975, "uri": "", "pos": "n", "ne": "", "item": "速度", "basic_words": ["速度"], "byte_length": 4, "formal": ""}, {"loc_details": [], "byte_offset": 981, "uri": "", "pos": "v", "ne": "", "item": "占据", "basic_words": ["占据"], "byte_length": 4, "formal": ""}, {"loc_details": [], "byte_offset": 989, "uri": "", "pos": "n", "ne": "", "item": "优势", "basic_words": ["优势"], "byte_length": 4, "formal": ""}, {"loc_details": [], "byte_offset": 997, "uri": "", "pos": "n", "ne": "", "item": "交接棒", "basic_words": ["交接", "棒"], "byte_length": 6, "formal": ""}, {"loc_details": [], "byte_offset": 1003, "uri": "", "pos": "n", "ne": "", "item": "时", "basic_words": ["时"], "byte_length": 2, "formal": ""}, {"loc_details": [], "byte_offset": 1007, "uri": "", "pos": "v", "ne": "", "item": "显得", "basic_words": ["显得"], "byte_length": 4, "formal": ""}, {"loc_details": [], "byte_offset": 1011, "uri": "", "pos": "vn", "ne": "", "item": "游刃有余", "basic_words": ["游刃有余"], "byte_length": 8, "formal": ""}, {"loc_details": [], "byte_offset": 1021, "uri": "", "pos": "v", "ne": "", "item": "接棒", "basic_words": ["接棒"], "byte_length": 4, "formal": ""}, {"loc_details": [], "byte_offset": 1029, "uri": "", "pos": "v", "ne": "", "item": "目视", "basic_words": ["目", "视"], "byte_length": 4, "formal": ""}, {"loc_details": [], "byte_offset": 1033, "uri": "", "pos": "s", "ne": "", "item": "前方", "basic_words": ["前方"], "byte_length": 4, "formal": ""}, {"loc_details": [], "byte_offset": 1041, "uri": "", "pos": "n", "ne": "", "item": "怠速", "basic_words": ["怠速"], "byte_length": 4, "formal": ""}, {"loc_details": [], "byte_offset": 1047, "uri": "", "pos": "n", "ne": "", "item": "右手", "basic_words": ["右手"], "byte_length": 4, "formal": ""}, {"loc_details": [], "byte_offset": 1051, "uri": "", "pos": "d", "ne": "", "item": "向后", "basic_words": ["向", "后"], "byte_length": 4, "formal": ""}, {"loc_details": [], "byte_offset": 1055, "uri": "", "pos": "d", "ne": "", "item": "微微", "basic_words": ["微微"], "byte_length": 4, "formal": ""}, {"loc_details": [], "byte_offset": 1059, "uri": "", "pos": "v", "ne": "", "item": "上翘", "basic_words": ["上翘"], "byte_length": 4, "formal": ""}, {"loc_details": [], "byte_offset": 1065, "uri": "", "pos": "v", "ne": "", "item": "交", "basic_words": ["交"], "byte_length": 2, "formal": ""}, {"loc_details": [], "byte_offset": 1067, "uri": "", "pos": "an", "ne": "", "item": "棒", "basic_words": ["棒"], "byte_length": 2, "formal": ""}, {"loc_details": [], "byte_offset": 1073, "uri": "", "pos": "v", "ne": "", "item": "总能", "basic_words": ["总", "能"], "byte_length": 4, "formal": ""}, {"loc_details": [], "byte_offset": 1085, "uri": "", "pos": "n", "ne": "", "item": "情况", "basic_words": ["情况"], "byte_length": 4, "formal": ""}, {"loc_details": [], "byte_offset": 1091, "uri": "", "pos": "ad", "ne": "", "item": "稳稳地", "basic_words": ["稳稳", "地"], "byte_length": 6, "formal": ""}, {"loc_details": [], "byte_offset": 1099, "uri": "", "pos": "an", "ne": "", "item": "棒", "basic_words": ["棒"], "byte_length": 2, "formal": ""}, {"loc_details": [], "byte_offset": 1101, "uri": "", "pos": "v", "ne": "", "item": "交", "basic_words": ["交"], "byte_length": 2, "formal": ""}, {"loc_details": [], "byte_offset": 1105, "uri": "", "pos": "n", "ne": "", "item": "队友", "basic_words": ["队友"], "byte_length": 4, "formal": ""}, {"loc_details": [], "byte_offset": 1109, "uri": "", "pos": "s", "ne": "", "item": "手上", "basic_words": ["手", "上"], "byte_length": 4, "formal": ""}, {"loc_details": [], "byte_offset": 1115, "uri": "", "pos": "nz", "ne": "", "item": "\n\n\n\n\t", "basic_words": ["\n\n\n", "\n\t"], "byte_length": 5, "formal": ""}, {"loc_details": [], "byte_offset": 1126, "uri": "", "pos": "m", "ne": "", "item": "四个", "basic_words": ["四", "个"], "byte_length": 4, "formal": ""}, {"loc_details": [], "byte_offset": 1130, "uri": "", "pos": "t", "ne": "", "item": "平时", "basic_words": ["平时"], "byte_length": 4, "formal": ""}, {"loc_details": [], "byte_offset": 1138, "uri": "", "pos": "a", "ne": "", "item": "要好", "basic_words": ["要", "好"], "byte_length": 4, "formal": ""}, {"loc_details": [], "byte_offset": 1144, "uri": "", "pos": "n", "ne": "", "item": "闺蜜", "basic_words": ["闺蜜"], "byte_length": 4, "formal": ""}, {"loc_details": [], "byte_offset": 1158, "uri": "", "pos": "v", "ne": "", "item": "相约", "basic_words": ["相约"], "byte_length": 4, "formal": ""}, {"loc_details": [], "byte_offset": 1162, "uri": "", "pos": "v", "ne": "", "item": "一起来", "basic_words": ["一", "起来"], "byte_length": 6, "formal": ""}, {"loc_details": [], "byte_offset": 1168, "uri": "", "pos": "nt", "ne": "", "item": "犀浦", "basic_words": ["犀浦"], "byte_length": 4, "formal": ""}, {"loc_details": [], "byte_offset": 1172, "uri": "", "pos": "v", "ne": "", "item": "参加", "basic_words": ["参加"], "byte_length": 4, "formal": ""}, {"loc_details": [], "byte_offset": 1176, "uri": "", "pos": "vn", "ne": "", "item": "比赛", "basic_words": ["比赛"], "byte_length": 4, "formal": ""}, {"loc_details": [], "byte_offset": 1184, "uri": "", "pos": "", "ne": "PER", "item": "张文莉", "basic_words": ["张文莉"], "byte_length": 6, "formal": ""}, {"loc_details": [], "byte_offset": 1190, "uri": "", "pos": "v", "ne": "", "item": "称", "basic_words": ["称"], "byte_length": 2, "formal": ""}, {"loc_details": [], "byte_offset": 1200, "uri": "", "pos": "n", "ne": "", "item": "队友", "basic_words": ["队友"], "byte_length": 4, "formal": ""}, {"loc_details": [], "byte_offset": 1204, "uri": "", "pos": "v", "ne": "", "item": "朝夕相处", "basic_words": ["朝夕相处"], "byte_length": 8, "formal": ""}, {"loc_details": [], "byte_offset": 1218, "uri": "", "pos": "a", "ne": "", "item": "默契", "basic_words": ["默契"], "byte_length": 4, "formal": ""}, {"loc_details": [], "byte_offset": 1222, "uri": "", "pos": "a", "ne": "", "item": "深厚", "basic_words": ["深厚"], "byte_length": 4, "formal": ""}, {"loc_details": [], "byte_offset": 1228, "uri": "", "pos": "v", "ne": "", "item": "比赛", "basic_words": ["比赛"], "byte_length": 4, "formal": ""}, {"loc_details": [], "byte_offset": 1232, "uri": "", "pos": "n", "ne": "", "item": "时", "basic_words": ["时"], "byte_length": 2, "formal": ""}, {"loc_details": [], "byte_offset": 1240, "uri": "", "pos": "v", "ne": "", "item": "信任", "basic_words": ["信任"], "byte_length": 4, "formal": ""}, {"loc_details": [], "byte_offset": 1252, "uri": "", "pos": "v", "ne": "", "item": "做好", "basic_words": ["做", "好"], "byte_length": 4, "formal": ""}, {"loc_details": [], "byte_offset": 1262, "uri": "", "pos": "n", "ne": "", "item": "工作", "basic_words": ["工作"], "byte_length": 4, "formal": ""}, {"loc_details": [], "byte_offset": 1276, "uri": "", "pos": "n", "ne": "", "item": "队友", "basic_words": ["队友"], "byte_length": 4, "formal": ""}, {"loc_details": [], "byte_offset": 1280, "uri": "", "pos": "v", "ne": "", "item": "表演", "basic_words": ["表演"], "byte_length": 4, "formal": ""}, {"loc_details": [], "byte_offset": 1288, "uri": "", "pos": "", "ne": "PER", "item": "张文莉", "basic_words": ["张文莉"], "byte_length": 6, "formal": ""}, {"loc_details": [], "byte_offset": 1294, "uri": "", "pos": "vd", "ne": "", "item": "笑着", "basic_words": ["笑着"], "byte_length": 4, "formal": ""}, {"loc_details": [], "byte_offset": 1298, "uri": "", "pos": "v", "ne": "", "item": "说", "basic_words": ["说"], "byte_length": 2, "formal": ""}, {"loc_details": [], "byte_offset": 1302, "uri": "", "pos": "nz", "ne": "", "item": "\n\n\n\n\n\n\n\n\t", "basic_words": ["\n\n\n", "\n\n\n", "\n\n\t"], "byte_length": 9, "formal": ""}, {"loc_details": [], "byte_offset": 1311, "uri": "", "pos": "n", "ne": "", "item": "仰卧起坐", "basic_words": ["仰卧", "起", "坐"], "byte_length": 8, "formal": ""}, {"loc_details": [], "byte_offset": 1323, "uri": "", "pos": "v", "ne": "", "item": "俯仰之间", "basic_words": ["俯仰之间"], "byte_length": 8, "formal": ""}, {"loc_details": [], "byte_offset": 1333, "uri": "", "pos": "n", "ne": "", "item": "力道", "basic_words": ["力道"], "byte_length": 4, "formal": ""}, {"loc_details": [], "byte_offset": 1337, "uri": "", "pos": "v", "ne": "", "item": "\n\n\n", "basic_words": ["\n\n\n"], "byte_length": 3, "formal": ""}, {"loc_details": [], "byte_offset": 1340, "uri": "", "pos": "v", "ne": "", "item": "\n\t", "basic_words": ["\n\t"], "byte_length": 2, "formal": ""}, {"loc_details": [], "byte_offset": 1342, "uri": "", "pos": "n", "ne": "", "item": "参赛选手", "basic_words": ["参赛", "选手"], "byte_length": 8, "formal": ""}, {"loc_details": [], "byte_offset": 1352, "uri": "", "pos": "n", "ne": "", "item": "裁判", "basic_words": ["裁判"], "byte_length": 4, "formal": ""}, {"loc_details": [], "byte_offset": 1358, "uri": "", "pos": "vn", "ne": "", "item": "安排", "basic_words": ["安排"], "byte_length": 4, "formal": ""}, {"loc_details": [], "byte_offset": 1364, "uri": "", "pos": "a", "ne": "", "item": "有序", "basic_words": ["有", "序"], "byte_length": 4, "formal": ""}, {"loc_details": [], "byte_offset": 1370, "uri": "", "pos": "v", "ne": "", "item": "平躺", "basic_words": ["平躺"], "byte_length": 4, "formal": ""}, {"loc_details": [], "byte_offset": 1386, "uri": "", "pos": "n", "ne": "", "item": "垫子", "basic_words": ["垫子"], "byte_length": 4, "formal": ""}, {"loc_details": [], "byte_offset": 1394, "uri": "", "pos": "n", "ne": "", "item": "双腿", "basic_words": ["双腿"], "byte_length": 4, "formal": ""}, {"loc_details": [], "byte_offset": 1398, "uri": "", "pos": "n", "ne": "", "item": "微曲", "basic_words": ["微曲"], "byte_length": 4, "formal": ""}, {"loc_details": [], "byte_offset": 1404, "uri": "", "pos": "n", "ne": "", "item": "双手", "basic_words": ["双手"], "byte_length": 4, "formal": ""}, {"loc_details": [], "byte_offset": 1408, "uri": "", "pos": "v", "ne": "", "item": "抱", "basic_words": ["抱"], "byte_length": 2, "formal": ""}, {"loc_details": [], "byte_offset": 1410, "uri": "", "pos": "n", "ne": "", "item": "头", "basic_words": ["头"], "byte_length": 2, "formal": ""}, {"loc_details": [], "byte_offset": 1414, "uri": "", "pos": "vn", "ne": "", "item": "工作", "basic_words": ["工作"], "byte_length": 4, "formal": ""}, {"loc_details": [], "byte_offset": 1418, "uri": "", "pos": "n", "ne": "", "item": "人员", "basic_words": ["人员"], "byte_length": 4, "formal": ""}, {"loc_details": [], "byte_offset": 1422, "uri": "", "pos": "v", "ne": "", "item": "辅助", "basic_words": ["辅助"], "byte_length": 4, "formal": ""}, {"loc_details": [], "byte_offset": 1426, "uri": "", "pos": "v", "ne": "", "item": "按压", "basic_words": ["按压"], "byte_length": 4, "formal": ""}, {"loc_details": [], "byte_offset": 1430, "uri": "", "pos": "n", "ne": "", "item": "选手", "basic_words": ["选手"], "byte_length": 4, "formal": ""}, {"loc_details": [], "byte_offset": 1436, "uri": "", "pos": "n", "ne": "", "item": "双脚", "basic_words": ["双脚"], "byte_length": 4, "formal": ""}, {"loc_details": [], "byte_offset": 1444, "uri": "", "pos": "d", "ne": "", "item": "为其", "basic_words": ["为", "其"], "byte_length": 4, "formal": ""}, {"loc_details": [], "byte_offset": 1448, "uri": "", "pos": "v", "ne": "", "item": "计数", "basic_words": ["计数"], "byte_length": 4, "formal": ""}, {"loc_details": [], "byte_offset": 1456, "uri": "", "pos": "v", "ne": "", "item": "俯", "basic_words": ["俯"], "byte_length": 2, "formal": ""}, {"loc_details": [], "byte_offset": 1460, "uri": "", "pos": "vn", "ne": "", "item": "仰", "basic_words": ["仰"], "byte_length": 2, "formal": ""}, {"loc_details": [], "byte_offset": 1472, "uri": "", "pos": "", "ne": "TIME", "item": "60秒钟", "basic_words": ["60", "秒", "钟"], "byte_length": 6, "formal": ""}, {"loc_details": [], "byte_offset": 1482, "uri": "", "pos": "m", "ne": "", "item": "一组", "basic_words": ["一", "组"], "byte_length": 4, "formal": ""}, {"loc_details": [], "byte_offset": 1490, "uri": "", "pos": "a", "ne": "", "item": "全", "basic_words": ["全"], "byte_length": 2, "formal": ""}, {"loc_details": [], "byte_offset": 1492, "uri": "", "pos": "n", "ne": "", "item": "组", "basic_words": ["组"], "byte_length": 2, "formal": ""}, {"loc_details": [], "byte_offset": 1494, "uri": "", "pos": "n", "ne": "", "item": "选手", "basic_words": ["选手"], "byte_length": 4, "formal": ""}, {"loc_details": [], "byte_offset": 1502, "uri": "", "pos": "v", "ne": "", "item": "就绪", "basic_words": ["就绪"], "byte_length": 4, "formal": ""}, {"loc_details": [], "byte_offset": 1510, "uri": "", "pos": "n", "ne": "", "item": "裁判", "basic_words": ["裁判"], "byte_length": 4, "formal": ""}, {"loc_details": [], "byte_offset": 1514, "uri": "", "pos": "n", "ne": "", "item": "口哨声", "basic_words": ["口哨", "声"], "byte_length": 6, "formal": ""}, {"loc_details": [], "byte_offset": 1522, "uri": "", "pos": "v", "ne": "", "item": "响", "basic_words": ["响"], "byte_length": 2, "formal": ""}, {"loc_details": [], "byte_offset": 1526, "uri": "", "pos": "vn", "ne": "", "item": "比赛", "basic_words": ["比赛"], "byte_length": 4, "formal": ""}, {"loc_details": [], "byte_offset": 1532, "uri": "", "pos": "ad", "ne": "", "item": "正式", "basic_words": ["正式"], "byte_length": 4, "formal": ""}, {"loc_details": [], "byte_offset": 1542, "uri": "", "pos": "nr", "ne": "", "item": "\n\n\n\n\t", "basic_words": ["\n\n\n", "\n\t"], "byte_length": 5, "formal": ""}, {"loc_details": [], "byte_offset": 1547, "uri": "", "pos": "v", "ne": "", "item": "比赛开始", "basic_words": ["比赛", "开始"], "byte_length": 8, "formal": ""}, {"loc_details": [], "byte_offset": 1557, "uri": "", "pos": "", "ne": "TIME", "item": "前三十秒", "basic_words": ["前", "三", "十", "秒"], "byte_length": 8, "formal": ""}, {"loc_details": [], "byte_offset": 1567, "uri": "", "pos": "n", "ne": "", "item": "选手们", "basic_words": ["选手", "们"], "byte_length": 6, "formal": ""}, {"loc_details": [], "byte_offset": 1575, "uri": "", "pos": "n", "ne": "", "item": "弓", "basic_words": ["弓"], "byte_length": 2, "formal": ""}, {"loc_details": [], "byte_offset": 1579, "uri": "", "pos": "n", "ne": "", "item": "弹", "basic_words": ["弹"], "byte_length": 2, "formal": ""}, {"loc_details": [], "byte_offset": 1585, "uri": "", "pos": "v", "ne": "", "item": "尽显", "basic_words": ["尽显"], "byte_length": 4, "formal": ""}, {"loc_details": [], "byte_offset": 1589, "uri": "", "pos": "an", "ne": "", "item": "灵活", "basic_words": ["灵活"], "byte_length": 4, "formal": ""}, {"loc_details": [], "byte_offset": 1595, "uri": "", "pos": "n", "ne": "", "item": "力道", "basic_words": ["力道"], "byte_length": 4, "formal": ""}, {"loc_details": [], "byte_offset": 1603, "uri": "", "pos": "", "ne": "TIME", "item": "三十秒", "basic_words": ["三", "十", "秒"], "byte_length": 6, "formal": ""}, {"loc_details": [], "byte_offset": 1613, "uri": "", "pos": "n", "ne": "", "item": "唇齿", "basic_words": ["唇齿"], "byte_length": 4, "formal": ""}, {"loc_details": [], "byte_offset": 1617, "uri": "", "pos": "v", "ne": "", "item": "紧闭", "basic_words": ["紧闭"], "byte_length": 4, "formal": ""}, {"loc_details": [], "byte_offset": 1621, "uri": "", "pos": "n", "ne": "", "item": "两颊", "basic_words": ["两颊"], "byte_length": 4, "formal": ""}, {"loc_details": [], "byte_offset": 1625, "uri": "", "pos": "a", "ne": "", "item": "通红", "basic_words": ["通", "红"], "byte_length": 4, "formal": ""}, {"loc_details": [], "byte_offset": 1631, "uri": "", "pos": "n", "ne": "", "item": "速度", "basic_words": ["速度"], "byte_length": 4, "formal": ""}, {"loc_details": [], "byte_offset": 1637, "uri": "", "pos": "n", "ne": "", "item": "角度", "basic_words": ["角度"], "byte_length": 4, "formal": ""}, {"loc_details": [], "byte_offset": 1643, "uri": "", "pos": "v", "ne": "", "item": "略显", "basic_words": ["略", "显"], "byte_length": 4, "formal": ""}, {"loc_details": [], "byte_offset": 1647, "uri": "", "pos": "an", "ne": "", "item": "吃力", "basic_words": ["吃力"], "byte_length": 4, "formal": ""}, {"loc_details": [], "byte_offset": 1653, "uri": "", "pos": "", "ne": "ORG", "item": "利兹学院", "basic_words": ["利兹", "学院"], "byte_length": 8, "formal": ""}, {"loc_details": [], "byte_offset": 1663, "uri": "", "pos": "", "ne": "PER", "item": "张铃婕", "basic_words": ["张铃婕"], "byte_length": 6, "formal": ""}, {"loc_details": [], "byte_offset": 1669, "uri": "", "pos": "n", "ne": "", "item": "同学", "basic_words": ["同学"], "byte_length": 4, "formal": ""}, {"loc_details": [], "byte_offset": 1673, "uri": "", "pos": "a", "ne": "", "item": "整齐", "basic_words": ["整齐"], "byte_length": 4, "formal": ""}, {"loc_details": [], "byte_offset": 1679, "uri": "", "pos": "n", "ne": "", "item": "发髻", "basic_words": ["发髻"], "byte_length": 4, "formal": ""}, {"loc_details": [], "byte_offset": 1685, "uri": "", "pos": "vn", "ne": "", "item": "比赛", "basic_words": ["比赛"], "byte_length": 4, "formal": ""}, {"loc_details": [], "byte_offset": 1689, "uri": "", "pos": "v", "ne": "", "item": "结束", "basic_words": ["结束"], "byte_length": 4, "formal": ""}, {"loc_details": [], "byte_offset": 1699, "uri": "", "pos": "v", "ne": "", "item": "略显", "basic_words": ["略", "显"], "byte_length": 4, "formal": ""}, {"loc_details": [], "byte_offset": 1703, "uri": "", "pos": "an", "ne": "", "item": "松散", "basic_words": ["松散"], "byte_length": 4, "formal": ""}, {"loc_details": [], "byte_offset": 1711, "uri": "", "pos": "v", "ne": "", "item": "叹", "basic_words": ["叹"], "byte_length": 2, "formal": ""}, {"loc_details": [], "byte_offset": 1715, "uri": "", "pos": "n", "ne": "", "item": "一口气", "basic_words": ["一口气"], "byte_length": 6, "formal": ""}, {"loc_details": [], "byte_offset": 1723, "uri": "", "pos": "n", "ne": "", "item": "记者", "basic_words": ["记者"], "byte_length": 4, "formal": ""}, {"loc_details": [], "byte_offset": 1727, "uri": "", "pos": "v", "ne": "", "item": "说", "basic_words": ["说"], "byte_length": 2, "formal": ""}, {"loc_details": [], "byte_offset": 1737, "uri": "", "pos": "a", "ne": "", "item": "真", "basic_words": ["真"], "byte_length": 2, "formal": ""}, {"loc_details": [], "byte_offset": 1743, "uri": "", "pos": "v", "ne": "", "item": "考验", "basic_words": ["考验"], "byte_length": 4, "formal": ""}, {"loc_details": [], "byte_offset": 1747, "uri": "", "pos": "n", "ne": "", "item": "腰部", "basic_words": ["腰部"], "byte_length": 4, "formal": ""}, {"loc_details": [], "byte_offset": 1751, "uri": "", "pos": "n", "ne": "", "item": "力量", "basic_words": ["力量"], "byte_length": 4, "formal": ""}, {"loc_details": [], "byte_offset": 1775, "uri": "", "pos": "n", "ne": "", "item": "力气", "basic_words": ["力气"], "byte_length": 4, "formal": ""}, {"loc_details": [], "byte_offset": 1795, "uri": "", "pos": "v", "ne": "", "item": "练", "basic_words": ["练"], "byte_length": 2, "formal": ""}, {"loc_details": [], "byte_offset": 1801, "uri": "", "pos": "nz", "ne": "", "item": "\n\n\n\n\t", "basic_words": ["\n\n\n", "\n\t"], "byte_length": 5, "formal": ""}, {"loc_details": [], "byte_offset": 1806, "uri": "", "pos": "n", "ne": "", "item": "男子", "basic_words": ["男子"], "byte_length": 4, "formal": ""}, {"loc_details": [], "byte_offset": 1810, "uri": "", "pos": "m", "ne": "", "item": "1000米", "basic_words": ["1000", "米"], "byte_length": 6, "formal": ""}, {"loc_details": [], "byte_offset": 1820, "uri": "", "pos": "v", "ne": "", "item": "辗转", "basic_words": ["辗转"], "byte_length": 4, "formal": ""}, {"loc_details": [], "byte_offset": 1826, "uri": "", "pos": "n", "ne": "", "item": "际", "basic_words": ["际"], "byte_length": 2, "formal": ""}, {"loc_details": [], "byte_offset": 1830, "uri": "", "pos": "v", "ne": "", "item": "坚定", "basic_words": ["坚定"], "byte_length": 4, "formal": ""}, {"loc_details": [], "byte_offset": 1834, "uri": "", "pos": "nr", "ne": "", "item": "\n\n\n\n\t", "basic_words": ["\n\n\n", "\n\t"], "byte_length": 5, "formal": ""}, {"loc_details": [], "byte_offset": 1841, "uri": "", "pos": "v", "ne": "", "item": "受", "basic_words": ["受"], "byte_length": 2, "formal": ""}, {"loc_details": [], "byte_offset": 1843, "uri": "", "pos": "vn", "ne": "", "item": "关注", "basic_words": ["关注"], "byte_length": 4, "formal": ""}, {"loc_details": [], "byte_offset": 1849, "uri": "", "pos": "n", "ne": "", "item": "男子", "basic_words": ["男子"], "byte_length": 4, "formal": ""}, {"loc_details": [], "byte_offset": 1853, "uri": "", "pos": "m", "ne": "", "item": "1000米", "basic_words": ["1000", "米"], "byte_length": 6, "formal": ""}, {"loc_details": [], "byte_offset": 1861, "uri": "", "pos": "n", "ne": "", "item": "中长跑", "basic_words": ["中", "长跑"], "byte_length": 6, "formal": ""}, {"loc_details": [], "byte_offset": 1867, "uri": "", "pos": "n", "ne": "", "item": "比赛", "basic_words": ["比赛"], "byte_length": 4, "formal": ""}, {"loc_details": [], "byte_offset": 1873, "uri": "", "pos": "", "ne": "TIME", "item": "下午三点二十", "basic_words": ["下午", "三", "点", "二", "十"], "byte_length": 12, "formal": ""}, {"loc_details": [], "byte_offset": 1885, "uri": "", "pos": "v", "ne": "", "item": "打响", "basic_words": ["打响"], "byte_length": 4, "formal": ""}, {"loc_details": [], "byte_offset": 1891, "uri": "", "pos": "m", "ne": "", "item": "第一声", "basic_words": ["第", "一", "声"], "byte_length": 6, "formal": ""}, {"loc_details": [], "byte_offset": 1897, "uri": "", "pos": "n", "ne": "", "item": "发令", "basic_words": ["发令"], "byte_length": 4, "formal": ""}, {"loc_details": [], "byte_offset": 1901, "uri": "", "pos": "n", "ne": "", "item": "枪", "basic_words": ["枪"], "byte_length": 2, "formal": ""}, {"loc_details": [], "byte_offset": 1907, "uri": "", "pos": "n", "ne": "", "item": "短跑", "basic_words": ["短跑"], "byte_length": 4, "formal": ""}, {"loc_details": [], "byte_offset": 1911, "uri": "", "pos": "n", "ne": "", "item": "比赛", "basic_words": ["比赛"], "byte_length": 4, "formal": ""}, {"loc_details": [], "byte_offset": 1925, "uri": "", "pos": "r", "ne": "", "item": "该项", "basic_words": ["该", "项"], "byte_length": 4, "formal": ""}, {"loc_details": [], "byte_offset": 1929, "uri": "", "pos": "n", "ne": "", "item": "比赛", "basic_words": ["比赛"], "byte_length": 4, "formal": ""}, {"loc_details": [], "byte_offset": 1935, "uri": "", "pos": "n", "ne": "", "item": "选手", "basic_words": ["选手"], "byte_length": 4, "formal": ""}, {"loc_details": [], "byte_offset": 1949, "uri": "", "pos": "v", "ne": "", "item": "跑", "basic_words": ["跑"], "byte_length": 2, "formal": ""}, {"loc_details": [], "byte_offset": 1953, "uri": "", "pos": "v", "ne": "", "item": "卯劲", "basic_words": ["卯劲"], "byte_length": 4, "formal": ""}, {"loc_details": [], "byte_offset": 1957, "uri": "", "pos": "n", "ne": "", "item": "前冲", "basic_words": ["前", "冲"], "byte_length": 4, "formal": ""}, {"loc_details": [], "byte_offset": 1973, "uri": "", "pos": "n", "ne": "", "item": "整体", "basic_words": ["整体"], "byte_length": 4, "formal": ""}, {"loc_details": [], "byte_offset": 1977, "uri": "", "pos": "n", "ne": "", "item": "位次", "basic_words": ["位次"], "byte_length": 4, "formal": ""}, {"loc_details": [], "byte_offset": 1987, "uri": "", "pos": "v", "ne": "", "item": "寻找", "basic_words": ["寻找"], "byte_length": 4, "formal": ""}, {"loc_details": [], "byte_offset": 1995, "uri": "", "pos": "n", "ne": "", "item": "步频", "basic_words": ["步频"], "byte_length": 4, "formal": ""}, {"loc_details": [], "byte_offset": 2001, "uri": "", "pos": "vn", "ne": "", "item": "呼吸", "basic_words": ["呼吸"], "byte_length": 4, "formal": ""}, {"loc_details": [], "byte_offset": 2007, "uri": "", "pos": "n", "ne": "", "item": "平衡点", "basic_words": ["平衡", "点"], "byte_length": 6, "formal": ""}, {"loc_details": [], "byte_offset": 2015, "uri": "", "pos": "v", "ne": "", "item": "蜂拥而上", "basic_words": ["蜂拥而上"], "byte_length": 8, "formal": ""}, {"loc_details": [], "byte_offset": 2025, "uri": "", "pos": "n", "ne": "", "item": "运动员", "basic_words": ["运动", "员"], "byte_length": 6, "formal": ""}, {"loc_details": [], "byte_offset": 2033, "uri": "", "pos": "t", "ne": "", "item": "一开始", "basic_words": ["一", "开始"], "byte_length": 6, "formal": ""}, {"loc_details": [], "byte_offset": 2039, "uri": "", "pos": "n", "ne": "", "item": "时", "basic_words": ["时"], "byte_length": 2, "formal": ""}, {"loc_details": [], "byte_offset": 2045, "uri": "", "pos": "ad", "ne": "", "item": "难", "basic_words": ["难"], "byte_length": 2, "formal": ""}, {"loc_details": [], "byte_offset": 2047, "uri": "", "pos": "v", "ne": "", "item": "分", "basic_words": ["分"], "byte_length": 2, "formal": ""}, {"loc_details": [], "byte_offset": 2049, "uri": "", "pos": "n", "ne": "", "item": "高下", "basic_words": ["高", "下"], "byte_length": 4, "formal": ""}, {"loc_details": [], "byte_offset": 2061, "uri": "", "pos": "m", "ne": "", "item": "第二圈", "basic_words": ["第", "二", "圈"], "byte_length": 6, "formal": ""}, {"loc_details": [], "byte_offset": 2079, "uri": "", "pos": "v", "ne": "", "item": "感觉到", "basic_words": ["感觉", "到"], "byte_length": 6, "formal": ""}, {"loc_details": [], "byte_offset": 2089, "uri": "", "pos": "vn", "ne": "", "item": "呼吸", "basic_words": ["呼吸"], "byte_length": 4, "formal": ""}, {"loc_details": [], "byte_offset": 2097, "uri": "", "pos": "a", "ne": "", "item": "急促", "basic_words": ["急促"], "byte_length": 4, "formal": ""}, {"loc_details": [], "byte_offset": 2105, "uri": "", "pos": "n", "ne": "", "item": "脚步", "basic_words": ["脚步"], "byte_length": 4, "formal": ""}, {"loc_details": [], "byte_offset": 2113, "uri": "", "pos": "a", "ne": "", "item": "沉重", "basic_words": ["沉重"], "byte_length": 4, "formal": ""}, {"loc_details": [], "byte_offset": 2121, "uri": "", "pos": "n", "ne": "", "item": "裁判", "basic_words": ["裁判"], "byte_length": 4, "formal": ""}, {"loc_details": [], "byte_offset": 2125, "uri": "", "pos": "v", "ne": "", "item": "站", "basic_words": ["站"], "byte_length": 2, "formal": ""}, {"loc_details": [], "byte_offset": 2129, "uri": "", "pos": "n", "ne": "", "item": "终点", "basic_words": ["终点"], "byte_length": 4, "formal": ""}, {"loc_details": [], "byte_offset": 2133, "uri": "", "pos": "n", "ne": "", "item": "处", "basic_words": ["处"], "byte_length": 2, "formal": ""}, {"loc_details": [], "byte_offset": 2141, "uri": "", "pos": "n", "ne": "", "item": "摇铃", "basic_words": ["摇铃"], "byte_length": 4, "formal": ""}, {"loc_details": [], "byte_offset": 2145, "uri": "", "pos": "v", "ne": "", "item": "鼓劲", "basic_words": ["鼓劲"], "byte_length": 4, "formal": ""}, {"loc_details": [], "byte_offset": 2151, "uri": "", "pos": "n", "ne": "", "item": "赛道", "basic_words": ["赛道"], "byte_length": 4, "formal": ""}, {"loc_details": [], "byte_offset": 2155, "uri": "", "pos": "f", "ne": "", "item": "两旁", "basic_words": ["两旁"], "byte_length": 4, "formal": ""}, {"loc_details": [], "byte_offset": 2161, "uri": "", "pos": "n", "ne": "", "item": "亲友", "basic_words": ["亲友"], "byte_length": 4, "formal": ""}, {"loc_details": [], "byte_offset": 2165, "uri": "", "pos": "n", "ne": "", "item": "团", "basic_words": ["团"], "byte_length": 2, "formal": ""}, {"loc_details": [], "byte_offset": 2171, "uri": "", "pos": "a", "ne": "", "item": "卖力", "basic_words": ["卖", "力"], "byte_length": 4, "formal": ""}, {"loc_details": [], "byte_offset": 2177, "uri": "", "pos": "v", "ne": "", "item": "呼喊", "basic_words": ["呼喊"], "byte_length": 4, "formal": ""}, {"loc_details": [], "byte_offset": 2189, "uri": "", "pos": "n", "ne": "", "item": "名字", "basic_words": ["名字"], "byte_length": 4, "formal": ""}, {"loc_details": [], "byte_offset": 2199, "uri": "", "pos": "v", "ne": "", "item": "加油", "basic_words": ["加油"], "byte_length": 4, "formal": ""}, {"loc_details": [], "byte_offset": 2203, "uri": "", "pos": "v", "ne": "", "item": "打气", "basic_words": ["打气"], "byte_length": 4, "formal": ""}, {"loc_details": [], "byte_offset": 2209, "uri": "", "pos": "m", "ne": "", "item": "一圈", "basic_words": ["一", "圈"], "byte_length": 4, "formal": ""}, {"loc_details": [], "byte_offset": 2215, "uri": "", "pos": "m", "ne": "", "item": "两圈", "basic_words": ["两", "圈"], "byte_length": 4, "formal": ""}, {"loc_details": [], "byte_offset": 2221, "uri": "", "pos": "m", "ne": "", "item": "两圈", "basic_words": ["两", "圈"], "byte_length": 4, "formal": ""}, {"loc_details": [], "byte_offset": 2229, "uri": "", "pos": "vn", "ne": "", "item": "辗转", "basic_words": ["辗转"], "byte_length": 4, "formal": ""}, {"loc_details": [], "byte_offset": 2237, "uri": "", "pos": "n", "ne": "", "item": "运动员们", "basic_words": ["运动", "员", "们"], "byte_length": 8, "formal": ""}, {"loc_details": [], "byte_offset": 2245, "uri": "", "pos": "d", "ne": "", "item": "终于", "basic_words": ["终于"], "byte_length": 4, "formal": ""}, {"loc_details": [], "byte_offset": 2249, "uri": "", "pos": "v", "ne": "", "item": "抵达", "basic_words": ["抵达"], "byte_length": 4, "formal": ""}, {"loc_details": [], "byte_offset": 2255, "uri": "", "pos": "n", "ne": "", "item": "终点", "basic_words": ["终点"], "byte_length": 4, "formal": ""}, {"loc_details": [], "byte_offset": 2261, "uri": "", "pos": "nr", "ne": "", "item": "\n\n\n\n\t", "basic_words": ["\n\n\n", "\n\t"], "byte_length": 5, "formal": ""}, {"loc_details": [], "byte_offset": 2272, "uri": "", "pos": "v", "ne": "", "item": "支撑", "basic_words": ["支撑"], "byte_length": 4, "formal": ""}, {"loc_details": [], "byte_offset": 2290, "uri": "", "pos": "n", "ne": "", "item": "男子", "basic_words": ["男子"], "byte_length": 4, "formal": ""}, {"loc_details": [], "byte_offset": 2294, "uri": "", "pos": "n", "ne": "", "item": "甲组", "basic_words": ["甲组"], "byte_length": 4, "formal": ""}, {"loc_details": [], "byte_offset": 2298, "uri": "", "pos": "n", "ne": "", "item": "冠军", "basic_words": ["冠军"], "byte_length": 4, "formal": ""}, {"loc_details": [], "byte_offset": 2302, "uri": "", "pos": "", "ne": "PER", "item": "杨松", "basic_words": ["杨松"], "byte_length": 4, "formal": ""}, {"loc_details": [], "byte_offset": 2306, "uri": "", "pos": "v", "ne": "", "item": "说", "basic_words": ["说"], "byte_length": 2, "formal": ""}, {"loc_details": [], "byte_offset": 2316, "uri": "", "pos": "v", "ne": "", "item": "想", "basic_words": ["想"], "byte_length": 2, "formal": ""}, {"loc_details": [], "byte_offset": 2324, "uri": "", "pos": "v", "ne": "", "item": "加油", "basic_words": ["加油"], "byte_length": 4, "formal": ""}, {"loc_details": [], "byte_offset": 2332, "uri": "", "pos": "a", "ne": "", "item": "失望", "basic_words": ["失望"], "byte_length": 4, "formal": ""}, {"loc_details": [], "byte_offset": 2344, "uri": "", "pos": "n", "ne": "", "item": "脑袋", "basic_words": ["脑袋"], "byte_length": 4, "formal": ""}, {"loc_details": [], "byte_offset": 2348, "uri": "", "pos": "f", "ne": "", "item": "里", "basic_words": ["里"], "byte_length": 2, "formal": ""}, {"loc_details": [], "byte_offset": 2354, "uri": "", "pos": "v", "ne": "", "item": "想着", "basic_words": ["想着"], "byte_length": 4, "formal": ""}, {"loc_details": [], "byte_offset": 2358, "uri": "", "pos": "d", "ne": "", "item": "快点", "basic_words": ["快点"], "byte_length": 4, "formal": ""}, {"loc_details": [], "byte_offset": 2362, "uri": "", "pos": "v", "ne": "", "item": "跑", "basic_words": ["跑"], "byte_length": 2, "formal": ""}, {"loc_details": [], "byte_offset": 2364, "uri": "", "pos": "d", "ne": "", "item": "快点", "basic_words": ["快点"], "byte_length": 4, "formal": ""}, {"loc_details": [], "byte_offset": 2368, "uri": "", "pos": "v", "ne": "", "item": "跑", "basic_words": ["跑"], "byte_length": 2, "formal": ""}, {"loc_details": [], "byte_offset": 2374, "uri": "", "pos": "n", "ne": "", "item": "乙", "basic_words": ["乙"], "byte_length": 2, "formal": ""}, {"loc_details": [], "byte_offset": 2376, "uri": "", "pos": "n", "ne": "", "item": "组", "basic_words": ["组"], "byte_length": 2, "formal": ""}, {"loc_details": [], "byte_offset": 2378, "uri": "", "pos": "n", "ne": "", "item": "冠军", "basic_words": ["冠军"], "byte_length": 4, "formal": ""}, {"loc_details": [], "byte_offset": 2388, "uri": "", "pos": "", "ne": "ORG", "item": "茅以升学院", "basic_words": ["茅以升", "学院"], "byte_length": 10, "formal": ""}, {"loc_details": [], "byte_offset": 2398, "uri": "", "pos": "n", "ne": "", "item": "大一", "basic_words": ["大一"], "byte_length": 4, "formal": ""}, {"loc_details": [], "byte_offset": 2404, "uri": "", "pos": "", "ne": "PER", "item": "王诗晨", "basic_words": ["王诗晨"], "byte_length": 6, "formal": ""}, {"loc_details": [], "byte_offset": 2414, "uri": "", "pos": "v", "ne": "", "item": "说", "basic_words": ["说"], "byte_length": 2, "formal": ""}, {"loc_details": [], "byte_offset": 2426, "uri": "", "pos": "v", "ne": "", "item": "想", "basic_words": ["想"], "byte_length": 2, "formal": ""}, {"loc_details": [], "byte_offset": 2434, "uri": "", "pos": "n", "ne": "", "item": "学院", "basic_words": ["学院"], "byte_length": 4, "formal": ""}, {"loc_details": [], "byte_offset": 2438, "uri": "", "pos": "v", "ne": "", "item": "争光", "basic_words": ["争光"], "byte_length": 4, "formal": ""}, {"loc_details": [], "byte_offset": 2448, "uri": "", "pos": "v", "ne": "", "item": "想", "basic_words": ["想"], "byte_length": 2, "formal": ""}, {"loc_details": [], "byte_offset": 2452, "uri": "", "pos": "n", "ne": "", "item": "大学", "basic_words": ["大学"], "byte_length": 4, "formal": ""}, {"loc_details": [], "byte_offset": 2456, "uri": "", "pos": "", "ne": "TIME", "item": "第一年", "basic_words": ["第", "一年"], "byte_length": 6, "formal": ""}, {"loc_details": [], "byte_offset": 2462, "uri": "", "pos": "v", "ne": "", "item": "证明", "basic_words": ["证明"], "byte_length": 4, "formal": ""}, {"loc_details": [], "byte_offset": 2470, "uri": "", "pos": "r", "ne": "", "item": "我自己", "basic_words": ["我", "自己"], "byte_length": 6, "formal": ""}, {"loc_details": [], "byte_offset": 2480, "uri": "", "pos": "nz", "ne": "", "item": "\n\n\n\n\t运动", "basic_words": ["\n\n\n", "\n\t", "运动"], "byte_length": 9, "formal": ""}, {"loc_details": [], "byte_offset": 2489, "uri": "", "pos": "n", "ne": "", "item": "健儿们", "basic_words": ["健", "儿", "们"], "byte_length": 6, "formal": ""}, {"loc_details": [], "byte_offset": 2503, "uri": "", "pos": "v", "ne": "", "item": "坚定", "basic_words": ["坚定"], "byte_length": 4, "formal": ""}, {"loc_details": [], "byte_offset": 2507, "uri": "", "pos": "n", "ne": "", "item": "信念", "basic_words": ["信念"], "byte_length": 4, "formal": ""}, {"loc_details": [], "byte_offset": 2513, "uri": "", "pos": "vn", "ne": "", "item": "支撑", "basic_words": ["支撑"], "byte_length": 4, "formal": ""}, {"loc_details": [], "byte_offset": 2519, "uri": "", "pos": "v", "ne": "", "item": "跑到", "basic_words": ["跑到"], "byte_length": 4, "formal": ""}, {"loc_details": [], "byte_offset": 2523, "uri": "", "pos": "n", "ne": "", "item": "终点", "basic_words": ["终点"], "byte_length": 4, "formal": ""}, {"loc_details": [], "byte_offset": 2533, "uri": "", "pos": "n", "ne": "", "item": "名次", "basic_words": ["名次"], "byte_length": 4, "formal": ""}, {"loc_details": [], "byte_offset": 2547, "uri": "", "pos": "v", "ne": "", "item": "都是", "basic_words": ["都", "是"], "byte_length": 4, "formal": ""}, {"loc_details": [], "byte_offset": 2551, "uri": "", "pos": "n", "ne": "", "item": "田径赛场", "basic_words": ["田径", "赛", "场"], "byte_length": 8, "formal": ""}, {"loc_details": [], "byte_offset": 2563, "uri": "", "pos": "n", "ne": "", "item": "英雄", "basic_words": ["英雄"], "byte_length": 4, "formal": ""}, {"loc_details": [], "byte_offset": 2569, "uri": "", "pos": "nz", "ne": "", "item": "\n\n\n\n\n\n\t", "basic_words": ["\n\n\n\n", "\n\n\t"], "byte_length": 7, "formal": ""}, {"loc_details": [], "byte_offset": 2576, "uri": "", "pos": "n", "ne": "", "item": "文字", "basic_words": ["文字"], "byte_length": 4, "formal": ""}, {"loc_details": [], "byte_offset": 2580, "uri": "", "pos": "n", "ne": "", "item": "记者", "basic_words": ["记者"], "byte_length": 4, "formal": ""}, {"loc_details": [], "byte_offset": 2586, "uri": "", "pos": "nr", "ne": "", "item": "周运静仪 徐斐  ", "basic_words": ["周", "运", "静", "仪", " ", "徐斐", "  "], "byte_length": 15, "formal": ""}, {"loc_details": [], "byte_offset": 2601, "uri": "", "pos": "vn", "ne": "", "item": "摄影", "basic_words": ["摄影"], "byte_length": 4, "formal": ""}, {"loc_details": [], "byte_offset": 2605, "uri": "", "pos": "n", "ne": "", "item": "记者", "basic_words": ["记者"], "byte_length": 4, "formal": ""}, {"loc_details": [], "byte_offset": 2611, "uri": "", "pos": "", "ne": "PER", "item": "张慧琴", "basic_words": ["张慧琴"], "byte_length": 6, "formal": ""}, {"loc_details": [], "byte_offset": 2617, "uri": "", "pos": "nz", "ne": "", "item": "\n\n\n\n\t ", "basic_words": ["\n\n\n", "\n\t "], "byte_length": 6, "formal": ""}]}